odoo/addons/web_widget_image_url/README.rst
odoo/addons/web_widget_image_url/__init__.py
odoo/addons/web_widget_image_url/__manifest__.py
odoo/addons/web_widget_image_url/i18n/web_widget_image_url.pot
odoo/addons/web_widget_image_url/static/description/icon.png
odoo/addons/web_widget_image_url/static/description/image.png
odoo/addons/web_widget_image_url/static/src/js/web_widget_image_url.js
odoo/addons/web_widget_image_url/static/src/xml/web_widget_image_url.xml
odoo/addons/web_widget_image_url/views/web_widget_image_url.xml
odoo11_addon_web_widget_image_url-11.0.1.0.1.dist-info/METADATA
odoo11_addon_web_widget_image_url-11.0.1.0.1.dist-info/WHEEL
odoo11_addon_web_widget_image_url-11.0.1.0.1.dist-info/top_level.txt
odoo11_addon_web_widget_image_url-11.0.1.0.1.dist-info/RECORD
